ProteinPlot/__init__.py
ProteinPlot/protplot.py
proteinplot-2.0.1.dist-info/METADATA
proteinplot-2.0.1.dist-info/WHEEL
proteinplot-2.0.1.dist-info/top_level.txt
proteinplot-2.0.1.dist-info/RECORD
