Metadata-Version: 2.4
Name: ProteinPlot
Version: 2.0.1
Summary: Library for managing .pdb extension, plotting
Home-page: https://protplot.readthedocs.io/en/latest/
Author: Poku-Racz-Denes
Author-email: denes.dome@gmail.com
Classifier: Programming Language :: Python :: 3
Classifier: License :: Other/Proprietary License
Classifier: Operating System :: OS Independent
Requires-Python: >=3.6
Requires-Dist: numpy
Requires-Dist: pandas
Requires-Dist: matplotlib
Requires-Dist: jupyter
Requires-Dist: plotly
Requires-Dist: seaborn
Dynamic: author
Dynamic: author-email
Dynamic: classifier
Dynamic: description
Dynamic: description-content-type
Dynamic: home-page
Dynamic: requires-dist
Dynamic: requires-python
Dynamic: summary
